{
  "ro": "ron",
  "pt": "por",
  "am": "amh",
  "ug": "uig",
  "ga": "gle",
  "bs": "bos",
  "mr": "mar",
  "tl": "tgl",
  "ja": "jpn",
  "ps": "pus",
  "ca": "cat",
  "ko": "kor",
  "yi": "yid",
  "sa": "san",
  "zh_tra": "chi_tra",
  "kn": "kan",
  "be": "bel",
  "en": "eng",
  "or": "ori",
  "bn": "ben",
  "my": "mya",
  "sv": "swe",
  "ms": "msa",
  "eu": "eus",
  "da": "dan",
  "no": "nor",
  "et": "est",
  "si": "sin",
  "ky": "kir",
  "ku": "kur",
  "vi": "vie",
  "sq": "sqi",
  "mk": "mkd",
  "ru": "rus",
  "sl": "slv",
  "chr": "chr",
  "syr": "syr",
  "ar": "ara",
  "fr": "fra",
  "uk": "ukr",
  "sr": "srp",
  "te": "tel",
  "th": "tha",
  "la": "lat",
  "gu": "guj",
  "tg": "tgk",
  "cs": "ces",
  "ceb": "ceb",
  "ka": "kat",
  "ne": "nep",
  "bg": "bul",
  "nl": "nld",
  "lt": "lit",
  "az": "aze",
  "lv": "lav",
  "ml": "mal",
  "pa": "pan",
  "mt": "mlt",
  "ht": "hat",
  "af": "afr",
  "bo": "bod",
  "is": "isl",
  "sk": "slk",
  "zh_sim": "chi_sim",
  "zh": "chi_sim",
  "de": "deu",
  "kk": "kaz",
  "pl": "pol",
  "fa": "fas",
  "hu": "hun",
  "fi": "fin",
  "frm": "frm",
  "uz": "uzb",
  "lo": "lao",
  "hr": "hrv",
  "iu": "iku",
  "ur": "urd",
  "he": "heb",
  "eo": "epo",
  "sw": "swa",
  "grc": "grc",
  "id": "ind",
  "dz": "dzo",
  "jv": "jav",
  "hi": "hin",
  "km": "khm",
  "tr": "tur",
  "ta": "tam",
  "cy": "cym",
  "es": "spa",
  "gl": "glg",
  "enm": "enm",
  "as": "asm",
  "it": "ita",
  "ti": "tir",
  "el": "ell"
}
